serial-stubs/METADATA.toml
serial-stubs/__init__.pyi
serial-stubs/__main__.pyi
serial-stubs/py.typed
serial-stubs/rfc2217.pyi
serial-stubs/rs485.pyi
serial-stubs/serialcli.pyi
serial-stubs/serialjava.pyi
serial-stubs/serialposix.pyi
serial-stubs/serialutil.pyi
serial-stubs/serialwin32.pyi
serial-stubs/win32.pyi
serial-stubs/threaded/__init__.pyi
serial-stubs/tools/__init__.pyi
serial-stubs/tools/hexlify_codec.pyi
serial-stubs/tools/list_ports.pyi
serial-stubs/tools/list_ports_common.pyi
serial-stubs/tools/list_ports_linux.pyi
serial-stubs/tools/list_ports_osx.pyi
serial-stubs/tools/list_ports_posix.pyi
serial-stubs/tools/list_ports_windows.pyi
serial-stubs/tools/miniterm.pyi
serial-stubs/urlhandler/__init__.pyi
serial-stubs/urlhandler/protocol_alt.pyi
serial-stubs/urlhandler/protocol_cp2110.pyi
serial-stubs/urlhandler/protocol_hwgrep.pyi
serial-stubs/urlhandler/protocol_loop.pyi
serial-stubs/urlhandler/protocol_rfc2217.pyi
serial-stubs/urlhandler/protocol_socket.pyi
serial-stubs/urlhandler/protocol_spy.pyi
types_pyserial-3.5.0.20250919.dist-info/licenses/LICENSE
types_pyserial-3.5.0.20250919.dist-info/METADATA
types_pyserial-3.5.0.20250919.dist-info/WHEEL
types_pyserial-3.5.0.20250919.dist-info/top_level.txt
types_pyserial-3.5.0.20250919.dist-info/RECORD
